fastfpe-0.2.0.dist-info/METADATA
fastfpe-0.2.0.dist-info/WHEEL
fastfpe-0.2.0.dist-info/licenses/LICENSE
fastfpe/__init__.py
fastfpe/_rust_fastfpe.pyd
fastfpe/ff1.py
fastfpe/ff1.pyi
fastfpe/ff3_1.py
fastfpe/ff3_1.pyi
fastfpe-0.2.0.dist-info/RECORD
