Metadata-Version: 2.4
Name: fastfpe
Version: 0.2.0
Classifier: Development Status :: 4 - Beta
Classifier: Intended Audience :: Developers
Classifier: License :: OSI Approved :: MIT License
Classifier: Programming Language :: Python :: 3.8
Classifier: Programming Language :: Python :: 3.9
Classifier: Programming Language :: Python :: 3.10
Classifier: Programming Language :: Python :: 3.11
Classifier: Programming Language :: Python :: 3.12
Classifier: Programming Language :: Python :: 3.13
Classifier: Programming Language :: Python :: 3.14
Classifier: Programming Language :: Rust
Classifier: Topic :: Security :: Cryptography
License-File: LICENSE
Summary: Fast Format Preserving Encryption (FPE) implementation in Rust
Author-email: Pedro Werneck <pedro.werneck@gmail.com>
License-Expression: MIT
Requires-Python: >=3.8
Project-URL: Repository, https://github.com/pjwerneck/fastfpe
Project-URL: Documentation, https://github.com/pjwerneck/fastfpe#readme
